cloudtrace/__init__.py
cloudtrace/fasttrace.py
cloudtrace/log.py
cloudtrace/pcap.c
cloudtrace/probe.c
cloudtrace/probe.cpython-37m-darwin.so
cloudtrace/trace.py
cloudtrace/utils.c
cloudtrace/utils.cpython-37m-darwin.so
cloudtrace/cloudtrace/__init__.py
cloudtrace/cloudtrace/pcap.cpython-37m-darwin.so
cloudtrace-0.0.5.dist-info/METADATA
cloudtrace-0.0.5.dist-info/WHEEL
cloudtrace-0.0.5.dist-info/entry_points.txt
cloudtrace-0.0.5.dist-info/top_level.txt
cloudtrace-0.0.5.dist-info/RECORD
