Metadata-Version: 2.1
Name: cloudtrace
Version: 0.0.5
Summary: Various packages for traceroute and BGP dump analysis.
Home-page: https://github.com/alexmarder/traceutils
Author: Alex Marder
License: UNKNOWN
Platform: UNKNOWN
Requires-Python: >3.6
Requires-Dist: cython
Requires-Dist: scapy
Requires-Dist: traceutils
